dxcode.py
dxcode-2.3.0.dist-info/METADATA
dxcode-2.3.0.dist-info/WHEEL
dxcode-2.3.0.dist-info/top_level.txt
dxcode-2.3.0.dist-info/RECORD
