Metadata-Version: 2.4
Name: dxcode
Version: 2.3.0
Summary: [dxcode] A distinctive, URL‑safe binary encoder with the signature `dx` prefix, CRC16 checksum, and smart compression.
Home-page: https://github.com/dogxii/dxcode
Author: Dogxi
Author-email: Dogxi <hi@dogxi.me>
License: MIT
Project-URL: Homepage, https://dxc.dogxi.me
Project-URL: Repository, https://github.com/dogxii/dxcode
Project-URL: Documentation, https://github.com/dogxii/dxcode#readme
Keywords: dx,dxcode,encoding,base64,dogxi,binary,text
Classifier: Development Status :: 5 - Production/Stable
Classifier: Intended Audience :: Developers
Classifier: License :: OSI Approved :: MIT License
Classifier: Programming Language :: Python :: 3
Classifier: Programming Language :: Python :: 3.7
Classifier: Programming Language :: Python :: 3.8
Classifier: Programming Language :: Python :: 3.9
Classifier: Programming Language :: Python :: 3.10
Classifier: Programming Language :: Python :: 3.11
Classifier: Programming Language :: Python :: 3.12
Requires-Python: >=3.7
Dynamic: author
Dynamic: home-page
Dynamic: requires-python
